{
  "run_id": "exp1a_hugo_1a_004_seed4",
  "experiment": "exp1a",
  "domain": "hugo",
  "config_id": "1a_004",
  "seed": 4,
  "timestamp": "2026-02-24T06:53:18.484885+00:00",
  "summary": {
    "accuracy_top1": 0.8516,
    "accuracy_by_category": {
      "same_flow": 0.9375,
      "switch_flow": 0.9531,
      "ambiguous_first": 0.625,
      "ambiguous_second": 0.8906
    },
    "accuracy_by_turn": {
      "turn_1": 0.7891,
      "turn_3": 0.9141
    },
    "latency_p50_ms": 2918,
    "latency_p95_ms": 5667,
    "input_tokens_total": 297262,
    "output_tokens_total": 16612,
    "failure_rate": 0.0
  },
  "migrated_from": "1d_005"
}